{
  "withWords": [
    {
      "x": 50,
      "y": 100,
      "width": 1800,
      "height": 120,
      "words": [
        { "text": "a", "x": 50, "y": 100, "width": 50, "height": 120 },
        {
          "text": "firstWord ",
          "x": 120,
          "y": 100,
          "width": 220,
          "height": 120
        },
        { "text": "on ", "x": 360, "y": 100, "width": 100, "height": 120 },
        { "text": "a ", "x": 480, "y": 100, "width": 50, "height": 120 },
        { "text": "line\n", "x": 550, "y": 100, "width": 260, "height": 120 }
      ]
    },
    {
      "x": 50,
      "y": 240,
      "width": 1800,
      "height": 120,
      "words": [
        { "text": "another ", "x": 50, "y": 240, "width": 300, "height": 120 },
        {
          "text": "secondWord ",
          "x": 420,
          "y": 240,
          "width": 220,
          "height": 120
        },
        { "text": "on ", "x": 660, "y": 240, "width": 100, "height": 120 },
        { "text": "another ", "x": 780, "y": 240, "width": 300, "height": 120 },
        { "text": "line\n", "x": 1150, "y": 240, "width": 260, "height": 120 }
      ]
    }
  ],
  "withoutWords": [
    {
      "x": 50,
      "y": 100,
      "width": 1800,
      "height": 120,
      "text": "a word on a line"
    },
    {
      "x": 50,
      "y": 240,
      "width": 1800,
      "height": 120,
      "text": "another word on another line"
    }
  ]
}
